{
  "data" : [
    {
      "crm" : "123",
      "nome" : "Joao da Silva",
      "especialidade" : "Cardiologista"
    },
    {
      "crm" : "312",
      "nome" : "Bruno Andrade",
      "especialidade" : "Cardiologista"
    },
    {
      "crm" : "1211233",
      "nome" : "Sérgio Luiz",
      "especialidade" : "Pediatra"
    },
    {
      "crm" : "13123123234",
      "nome" : "Márcia Andrade",
      "especialidade" : "Câncer"
    },
    {
      "crm" : "678546",
      "nome" : "Bezerra da Silva",
      "especialidade" : "Cardiologista"
    }
  ]
}